overwatchpy/__init__.py
overwatchpy/api.py
overwatchpy/const.py
overwatchpy/core.py
overwatchpy/errors.py
overwatchpy/objects.py
overwatchpy-0.0.4.dist-info/METADATA
overwatchpy-0.0.4.dist-info/WHEEL
overwatchpy-0.0.4.dist-info/RECORD
