Metadata-Version: 2.1
Name: overwatchpy
Version: 0.0.4
Summary: Python wrapper for Overwatch API
Author: alexraskin
Author-email: alexgithub@fastmail.fm
Requires-Python: >=3.11,<4.0
Classifier: Programming Language :: Python :: 3
Classifier: Programming Language :: Python :: 3.11
Requires-Dist: requests (>=2.31.0,<3.0.0)
